{"assigned": {"Welcome.html": 0, "Task.html": 0, "Certainty.html": 0, "Certainty Examples.html": 0, "Navigation.html": 0, "Consent.html": 0, "Experience.html": 0, "End.html": 0, "Psychology_tweet_144_p": ["5f4539491d5a4f0ce250990a"], "Psychology_tweet_144_r": ["5f4539491d5a4f0ce250990a"], "Psychology_tweet_220_p": ["5f4539491d5a4f0ce250990a"], "Psychology_tweet_220_r": ["5f4539491d5a4f0ce250990a"], "Psychology_tweet_45_p": ["5f4539491d5a4f0ce250990a"], "Psychology_tweet_45_r": ["5f4539491d5a4f0ce250990a"], "Psychology_510_p": ["5f4539491d5a4f0ce250990a"], "Psychology_510_r": ["5f4539491d5a4f0ce250990a"], "Psychology_21_p": ["5f4539491d5a4f0ce250990a"], "Psychology_21_r": ["5f4539491d5a4f0ce250990a"], "Psychology_tweet_82_p": ["5f4539491d5a4f0ce250990a"], "Psychology_tweet_82_r": ["5f4539491d5a4f0ce250990a"], "test_question_testing_Somewhat uncertain": ["5f4539491d5a4f0ce250990a"], "test_question_testing_Certain": ["5f4539491d5a4f0ce250990a"]}, "unassigned": {"Psychology_62_p": 1, "Psychology_62_r": 1, "Psychology_229_p": 1}, "testing": {"test_question_per_annotator": 2, "ids": ["test_question_testing_Uncertain", "test_question_testing_Certain", "test_question_testing_Somewhat certain", "test_question_testing_Somewhat uncertain"]}, "prestudy_ids": [], "prestudy_passed_users": [], "prestudy_failed_users": [], "pre_annotation_pages": ["Welcome.html", "Task.html", "Certainty.html", "Certainty Examples.html", "Navigation.html", "Consent.html"], "post_annotation_pages": ["Experience.html", "End.html"]}